tsuchinoko/__init__.py
tsuchinoko/_bootstrap.py
tsuchinoko/_version.py
tsuchinoko/adaptive/__init__.py
tsuchinoko/adaptive/_adaptive.py
tsuchinoko/adaptive/acquisition_functions.py
tsuchinoko/adaptive/adaptive.py
tsuchinoko/adaptive/fvgp_gpCAM_in_process.py
tsuchinoko/adaptive/gpCAM_in_process.py
tsuchinoko/adaptive/grid.py
tsuchinoko/adaptive/quadtree.py
tsuchinoko/adaptive/random_in_process.py
tsuchinoko/assets/__init__.py
tsuchinoko/assets/tsuchinoko.icns
tsuchinoko/assets/tsuchinoko.ico
tsuchinoko/assets/tsuchinoko.png
tsuchinoko/core/__init__.py
tsuchinoko/core/messages.py
tsuchinoko/examples/IRBL_server_demo_LC.py
tsuchinoko/examples/__init__.py
tsuchinoko/examples/_launch_demo.py
tsuchinoko/examples/adaptive_demo.py
tsuchinoko/examples/bluesky_adaptive_demo.py
tsuchinoko/examples/client_demo.py
tsuchinoko/examples/gi_tomo.py
tsuchinoko/examples/gi_tomo_analysis.py
tsuchinoko/examples/gi_tomo_measure.py
tsuchinoko/examples/gi_tomo_phantom.py
tsuchinoko/examples/grid_demo.py
tsuchinoko/examples/headless_demo.py
tsuchinoko/examples/high_dimensionality_server_demo.py
tsuchinoko/examples/ir_server_demo.py
tsuchinoko/examples/multi_task_server_demo.py
tsuchinoko/examples/peak1.png
tsuchinoko/examples/peak2.png
tsuchinoko/examples/phantom.png
tsuchinoko/examples/quadtree_demo.py
tsuchinoko/examples/server_demo.py
tsuchinoko/examples/server_demo_bluesky.py
tsuchinoko/examples/simplest_demo.py
tsuchinoko/examples/sombrero_pug.jpg
tsuchinoko/examples/vector_metric_demo.py
tsuchinoko/examples/deprecated/demo.py
tsuchinoko/examples/deprecated/demo2.py
tsuchinoko/examples/deprecated/main.py
tsuchinoko/execution/__init__.py
tsuchinoko/execution/bluesky_adaptive.py
tsuchinoko/execution/bluesky_in_process.py
tsuchinoko/execution/simple.py
tsuchinoko/execution/threaded_in_process.py
tsuchinoko/extensions/__init__.py
tsuchinoko/graphics_items/__init__.py
tsuchinoko/graphics_items/clouditem.py
tsuchinoko/graphics_items/indicatoritem.py
tsuchinoko/graphics_items/mixins.py
tsuchinoko-1.1.27.dist-info/METADATA
tsuchinoko-1.1.27.dist-info/WHEEL
tsuchinoko-1.1.27.dist-info/entry_points.txt
tsuchinoko-1.1.27.dist-info/licenses/AUTHORS.rst
tsuchinoko-1.1.27.dist-info/licenses/LICENSE
tsuchinoko-1.1.27.dist-info/RECORD
