Metadata-Version: 2.4
Name: tsuchinoko
Version: 1.1.27
Summary: A Qt application for adaptive experiment tuning and execution 
Project-URL: Homepage, https://tsuchinoko.readthedocs.io/
Project-URL: Documentation, https://tsuchinoko.readthedocs.io/
Project-URL: Repository, https://github.com/lbl-camera/tsuchinoko.git
Project-URL: Bug Tracker, https://github.com/lbl-camera/tsuchinoko/issues
Project-URL: Changelog, https://github.com/lbl-camera/tsuchinoko/commits/master/
Author-email: "Ronald J. Pandolfi" <ronpandolfi@lbl.gov>
Maintainer-email: "Ronald J. Pandolfi" <ronpandolfi@lbl.gov>
License-Expression: GPL-3.0-only
License-File: AUTHORS.rst
License-File: LICENSE
Keywords: adaptive,autonomous,gui,qt,self driving
Classifier: Development Status :: 4 - Beta
Classifier: License :: OSI Approved :: GNU General Public License v3 or later (GPLv3+)
Classifier: Natural Language :: English
Classifier: Programming Language :: Python :: 3
Requires-Python: >=3.9
Requires-Dist: appdirs
Requires-Dist: bluesky
Requires-Dist: click
Requires-Dist: fvgp~=4.6.5
Requires-Dist: gpcam~=8.2.3
Requires-Dist: loguru
Requires-Dist: numpy
Requires-Dist: ophyd
Requires-Dist: pillow
Requires-Dist: pyopengl
Requires-Dist: pyopengl-accelerate
Requires-Dist: pyqode-core
Requires-Dist: pyqode-python
Requires-Dist: pyqtgraph
Requires-Dist: pyside6<6.9.1
Requires-Dist: qtconsole
Requires-Dist: qtmodern
Requires-Dist: qtpy
Requires-Dist: scikit-learn
Requires-Dist: scipy
Provides-Extra: dev
Requires-Dist: pillow; extra == 'dev'
Requires-Dist: pyinstaller; extra == 'dev'
Provides-Extra: docs
Requires-Dist: matplotlib; extra == 'docs'
Requires-Dist: myst-parser; extra == 'docs'
Requires-Dist: numpydoc; extra == 'docs'
Requires-Dist: sphinx; extra == 'docs'
Requires-Dist: sphinx-copybutton; extra == 'docs'
Requires-Dist: sphinx-markdown-tables; extra == 'docs'
Requires-Dist: sphinx-rtd-dark-mode; extra == 'docs'
Requires-Dist: sphinx-rtd-theme; extra == 'docs'
Provides-Extra: tests
Requires-Dist: codecov; extra == 'tests'
Requires-Dist: coverage; extra == 'tests'
Requires-Dist: coveralls; extra == 'tests'
Requires-Dist: pillow; extra == 'tests'
Requires-Dist: pylint; extra == 'tests'
Requires-Dist: pytest-cov; extra == 'tests'
Requires-Dist: pytest-lazy-fixture; extra == 'tests'
Requires-Dist: pytest-qt; extra == 'tests'
Requires-Dist: pytest<8; extra == 'tests'
